{
    "catppuccin-fcitx5": {
        "cargoLocks": null,
        "date": "2024-09-01",
        "extract": null,
        "name": "catppuccin-fcitx5",
        "passthru": null,
        "pinned": false,
        "src": {
            "deepClone": false,
            "fetchSubmodules": false,
            "leaveDotGit": false,
            "name": null,
            "rev": "3471b918d4b5aab2d3c3dd9f2c3b9c18fb470e8e",
            "sha256": "sha256-1IqFVTEY6z8yNjpi5C+wahMN1kpt0OJATy5echjPXmc=",
            "sparseCheckout": [],
            "type": "git",
            "url": "https://github.com/catppuccin/fcitx5"
        },
        "version": "3471b918d4b5aab2d3c3dd9f2c3b9c18fb470e8e"
    },
    "firefox-gnome-theme": {
        "cargoLocks": null,
        "date": "2024-10-11",
        "extract": null,
        "name": "firefox-gnome-theme",
        "passthru": null,
        "pinned": false,
        "src": {
            "deepClone": false,
            "fetchSubmodules": false,
            "leaveDotGit": false,
            "name": null,
            "rev": "e53b84d428e7f5ba0f04d6a91e6cc6c05c75b632",
            "sha256": "sha256-J53bks/1loTdXiSQz1OlOAc8jx9g399oF1YiXAX2JKQ=",
            "sparseCheckout": [],
            "type": "git",
            "url": "https://github.com/rafaelmardojai/firefox-gnome-theme"
        },
        "version": "e53b84d428e7f5ba0f04d6a91e6cc6c05c75b632"
    },
    "san-francisco-pro": {
        "cargoLocks": null,
        "date": "2021-06-22",
        "extract": null,
        "name": "san-francisco-pro",
        "passthru": null,
        "pinned": false,
        "src": {
            "deepClone": false,
            "fetchSubmodules": false,
            "leaveDotGit": false,
            "name": null,
            "rev": "8bfea09aa6f1139479f80358b2e1e5c6dc991a58",
            "sha256": "sha256-mAXExj8n8gFHq19HfGy4UOJYKVGPYgarGd/04kUIqX4=",
            "sparseCheckout": [],
            "type": "git",
            "url": "https://github.com/sahibjotsaggu/San-Francisco-Pro-Fonts"
        },
        "version": "8bfea09aa6f1139479f80358b2e1e5c6dc991a58"
    },
    "waybar": {
        "cargoLocks": null,
        "date": "2024-10-01",
        "extract": null,
        "name": "waybar",
        "passthru": null,
        "pinned": false,
        "src": {
            "deepClone": false,
            "fetchSubmodules": false,
            "leaveDotGit": false,
            "name": null,
            "rev": "280f11e247bc264541bb7daa01ffcce9fe6721a1",
            "sha256": "sha256-m1KNJf5HkY9myhtNMhgd2XZGJ2lqWMD1jDi4NgDCfoQ=",
            "sparseCheckout": [],
            "type": "git",
            "url": "https://github.com/alexays/waybar"
        },
        "version": "280f11e247bc264541bb7daa01ffcce9fe6721a1"
    },
    "wezterm": {
        "cargoLocks": {
            "Cargo.lock": [
                "./wezterm-9ddca7bde92090792dbcdc65c1e9897c362196d7/Cargo.lock",
                {
                    "sqlite-cache-0.1.3": "sha256-sBAC8MsQZgH+dcWpoxzq9iw5078vwzCijgyQnMOWIkk=",
                    "xcb-imdkit-0.3.0": "sha256-77KaJO+QJWy3tJ9AF1TXKaQHpoVOfGIRqteyqpQaSWo="
                }
            ]
        },
        "date": "2024-10-15",
        "extract": null,
        "name": "wezterm",
        "passthru": null,
        "pinned": false,
        "src": {
            "deepClone": false,
            "fetchSubmodules": true,
            "leaveDotGit": false,
            "name": null,
            "rev": "9ddca7bde92090792dbcdc65c1e9897c362196d7",
            "sha256": "sha256-BC+qJ54hF+iFtq15/ygQNHjLUkncWmM2ueIMDwjGmiE=",
            "sparseCheckout": [],
            "type": "git",
            "url": "https://github.com/wez/wezterm"
        },
        "version": "9ddca7bde92090792dbcdc65c1e9897c362196d7"
    },
    "whitesur-gtk-theme": {
        "cargoLocks": null,
        "date": "2024-10-15",
        "extract": null,
        "name": "whitesur-gtk-theme",
        "passthru": null,
        "pinned": false,
        "src": {
            "deepClone": false,
            "fetchSubmodules": false,
            "leaveDotGit": false,
            "name": null,
            "rev": "5d09b0610ba3fd720afe715e1be9aafaeadcd33c",
            "sha256": "sha256-pF3oau2/a0dCqbz3t8e3tDoaYrii+J3m3K+eUvcUgpM=",
            "sparseCheckout": [],
            "type": "git",
            "url": "https://github.com/vinceliuice/WhiteSur-gtk-theme"
        },
        "version": "5d09b0610ba3fd720afe715e1be9aafaeadcd33c"
    }
}